opencv_draw_tools/SelectZone.py
opencv_draw_tools/__init__.py
opencv_draw_tools/tags_constraint.py
opencv_draw_tools_fernaperg-1.2.0.dist-info/LICENSE
opencv_draw_tools_fernaperg-1.2.0.dist-info/METADATA
opencv_draw_tools_fernaperg-1.2.0.dist-info/WHEEL
opencv_draw_tools_fernaperg-1.2.0.dist-info/top_level.txt
opencv_draw_tools_fernaperg-1.2.0.dist-info/RECORD
