Metadata-Version: 2.1
Name: opencv-draw-tools-fernaperg
Version: 1.2.0
Summary: Library to help the drawing process with OpenCV. Thought to add labels to the images. Classification of images, etc.
Home-page: https://github.com/fernaper/opencv-draw-tools
Author: Fernando Pérez
Author-email: fernaperg@gmail.com
License: MIT
Platform: UNKNOWN
Classifier: Programming Language :: Python :: 3
Classifier: License :: OSI Approved :: MIT License
Classifier: Operating System :: OS Independent
Requires-Dist: numpy
Requires-Dist: python-constraint
